qiwugrader/__init__.py
qiwugrader/app.py
qiwugrader/compare.py
qiwugrader/generate.py
qiwugrader/server.py
qiwugrader/controller/__init__.py
qiwugrader/controller/basic_handler.py
qiwugrader/controller/config_file_handler.py
qiwugrader/controller/private_msg_handler.py
qiwugrader/controller/single_dialogue_handler.py
qiwugrader/grader/__init__.py
qiwugrader/grader/compatible.py
qiwugrader/grader/dns_cache.py
qiwugrader/grader/grader_core.py
qiwugrader/grader/grader_multitask.py
qiwugrader/grader/init.py
qiwugrader/model/__init__.py
qiwugrader/model/case_generator.py
qiwugrader/model/shared_counter.py
qiwugrader/request/__init__.py
qiwugrader/request/basic_request.py
qiwugrader/request/chat_api.py
qiwugrader/request/chat_robot.py
qiwugrader/request/chat_robot_redis.py
qiwugrader/request/single_dialogue.py
qiwugrader/util/__init__.py
qiwugrader/util/recorder.py
qiwugrader/util/string_helper.py
qiwugrader/view/__init__.py
qiwugrader/view/config_file_view.py
qiwugrader/view/test_view.py
QiwuGrader-1.9.8.dist-info/LICENSE
QiwuGrader-1.9.8.dist-info/METADATA
QiwuGrader-1.9.8.dist-info/WHEEL
QiwuGrader-1.9.8.dist-info/entry_points.txt
QiwuGrader-1.9.8.dist-info/top_level.txt
QiwuGrader-1.9.8.dist-info/RECORD
