Metadata-Version: 2.1
Name: QiwuGrader
Version: 1.9.8
Summary: Qiwu auto test tool, supports accuracy/pressure tests for knowledge base, QA API and server backend
Home-page: https://github.com/noahzark/QiwuGrader
Author: noahzark
Author-email: lfzh1993@gmail.com
License: UNKNOWN
Project-URL: Bug Reports, https://github.com/noahzark/QiwuGrader/issues
Project-URL: Say Thanks!, https://qiwu.ai
Project-URL: Source, https://github.com/noahzark/QiwuGrader
Keywords: qiwu qiwugrader
Platform: UNKNOWN
Classifier: Development Status :: 5 - Production/Stable
Classifier: Intended Audience :: Developers
Classifier: Topic :: Software Development :: Testing
Classifier: License :: OSI Approved :: GNU General Public License v3 (GPLv3)
Classifier: Programming Language :: Python :: 2
Classifier: Programming Language :: Python :: 2.7
Classifier: Programming Language :: Python :: 3
Classifier: Programming Language :: Python :: 3.6
Classifier: Programming Language :: Python :: 3.7
Requires-Dist: requests
Requires-Dist: pyyaml
Requires-Dist: enum34
Requires-Dist: xlrd
Requires-Dist: gevent
Provides-Extra: pyqt5
Requires-Dist: pyqt5 ; extra == 'pyqt5'
Provides-Extra: srt
Requires-Dist: srt ; extra == 'srt'
